ormparams/__init__.py
ormparams/fastapi_ext.py
ormparams/core/__init__.py
ormparams/core/exceptions.py
ormparams/core/filter.py
ormparams/core/mixin.py
ormparams/core/parser.py
ormparams/core/policy.py
ormparams/core/suffixes.py
ormparams/core/types.py
ormparamsv1/__init__.py
ormparamsv1/exceptions.py
ormparamsv1/fastapi_ext.py
ormparamsv1/filter.py
ormparamsv1/mixin.py
ormparamsv1/parser.py
ormparamsv1/rules.py
ormparamsv1/suffixes.py
ormparams-2.0.3.dist-info/METADATA
ormparams-2.0.3.dist-info/WHEEL
ormparams-2.0.3.dist-info/top_level.txt
ormparams-2.0.3.dist-info/RECORD
