Metadata-Version: 2.4
Name: ormparams
Version: 2.0.3
Summary: Query parameter parser and filter for ORM-based applications
Author-email: AntonKochurka <antonkotchurka@email.com>
License: MIT
Requires-Python: >=3.9
Requires-Dist: sqlalchemy
Provides-Extra: fastapi
Requires-Dist: fastapi>=0.100; extra == "fastapi"
Requires-Dist: pydantic>=2.0; extra == "fastapi"
